{"cameraMode":{"drawMode":0,"name":"Shaded","section":"Shading Mode"},"sceneLighting":false,"audioPlay":false,"sceneViewState":{"showFog":true,"showMaterialUpdate":false,"showSkybox":false,"showFlares":true,"showImageEffects":true,"showParticleSystems":true},"in2DMode":false,"pivot":{"x":-0.067852683365345,"y":2.1410882472991945,"z":3.2922966480255129},"rotation":{"x":-0.033570535480976108,"y":0.966262698173523,"z":-0.18965168297290803,"w":-0.17104247212409974},"size":10.068218231201172,"orthographic":false}